igi_gc_reader/__init__.py
igi_gc_reader/app.py
igi_gc_reader/sample_data.py
igi_gc_reader/utils.py
igi_gc_reader/writer.py
igi_gc_reader/reader/__init__.py
igi_gc_reader/reader/classification.py
igi_gc_reader/reader/context_data.py
igi_gc_reader/reader/excel_address.py
igi_gc_reader/reader/excel_reader.py
igi_gc_reader/reader/gc_page.py
igi_gc_reader/reader/gc_reader.py
igi_gc_reader-0.1.3.dist-info/METADATA
igi_gc_reader-0.1.3.dist-info/WHEEL
igi_gc_reader-0.1.3.dist-info/licence.txt
igi_gc_reader-0.1.3.dist-info/top_level.txt
igi_gc_reader-0.1.3.dist-info/RECORD
